web3automation/__init__.py
web3automation/web3automation.py
web3automation-1.1.7.dist-info/METADATA
web3automation-1.1.7.dist-info/WHEEL
web3automation-1.1.7.dist-info/top_level.txt
web3automation-1.1.7.dist-info/RECORD
