Metadata-Version: 2.1
Name: web3automation
Version: 1.1.7
Summary: web automation for web3
Home-page: https://github.com/username/my_package
Author: zack
Classifier: Programming Language :: Python :: 3
Classifier: License :: OSI Approved :: MIT License
Classifier: Operating System :: OS Independent
Requires-Python: >=3.6
